README.md
setup.cfg
setup.py
GitHubCommitsDownloader/Downloader.py
GitHubCommitsDownloader/GitHub.py
GitHubCommitsDownloader/__init__.py
GitHubCommitsDownloader/clear.py
GitHubCommitsDownloader/exec.py
GitHubCommitsDownloader/getTerminalSize.py
GitHubCommitsDownloader/log.py
GitHubCommitsDownloader/mkdir.py
GitHubCommitsDownloader/parse.py
GitHubCommitsDownloader/parseOptions.py
GitHubCommitsDownloader/ques.py
GitHubCommitsDownloader/request.py
GitHubCommitsDownloader/wait.py
GitHubCommitsDownloader.egg-info/PKG-INFO
GitHubCommitsDownloader.egg-info/SOURCES.txt
GitHubCommitsDownloader.egg-info/dependency_links.txt
GitHubCommitsDownloader.egg-info/entry_points.txt
GitHubCommitsDownloader.egg-info/requires.txt
GitHubCommitsDownloader.egg-info/top_level.txt