Metadata-Version: 2.1
Name: GitHubCommitsDownloader
Version: 1.3.5
Summary: Github Commits Downloader App
Home-page: https://github.com/MDReal32/GitHubCommitsDownloader
Author: MDReal
Author-email: vminecrafter2015@gmail.com
License: MIT
Download-URL: https://github.com/MDReal32/GitHubCommitsDownloader/archive/master.zip
Keywords: ss,github,commits,downloader,github commits downloader,githubcommitsdownloader
Platform: UNKNOWN
Classifier: Programming Language :: Python :: 3
Classifier: Programming Language :: Python :: 3.8
Requires-Python: >=3.8
